backports.time_perf_counter-0.0.4-py3.4-nspkg.pth
backports/time_perf_counter/__init__.py
backports.time_perf_counter-0.0.4.dist-info/LICENSE.rst
backports.time_perf_counter-0.0.4.dist-info/METADATA
backports.time_perf_counter-0.0.4.dist-info/WHEEL
backports.time_perf_counter-0.0.4.dist-info/namespace_packages.txt
backports.time_perf_counter-0.0.4.dist-info/top_level.txt
backports.time_perf_counter-0.0.4.dist-info/RECORD
