Metadata-Version: 2.1
Name: backports.time-perf-counter
Version: 0.0.4
Summary: time.perf_counter() for Python < 3.3
Home-page: https://github.com/ejd/backports.time_perf_counter
Author: Eric Dramstad
Author-email: edrams@gmail.com
License: MIT
Platform: UNKNOWN
Classifier: Development Status :: 3 - Alpha
Classifier: Intended Audience :: Developers
Classifier: License :: OSI Approved :: MIT License
Classifier: Operating System :: OS Independent
Classifier: Programming Language :: Python :: 2
Classifier: Programming Language :: Python :: 3
Requires-Dist: setuptools
Requires-Dist: monotonic ; python_version < "3.3"
